MultiTable/__init__.py
MultiTable/main.py
MultiTable-0.0.1.dist-info/LICENSE.txt
MultiTable-0.0.1.dist-info/METADATA
MultiTable-0.0.1.dist-info/WHEEL
MultiTable-0.0.1.dist-info/top_level.txt
MultiTable-0.0.1.dist-info/RECORD
