Metadata-Version: 2.1
Name: MultiTable
Version: 0.0.1
Summary: A Multiplication Table Printer
Home-page: https://github.com/vihaanpundir/multitable
Author: Vihaan Pundir
Author-email: vihaan.pundir26@gmail.com
License: UNKNOWN
Project-URL: Bug Tracker, https://github.com/vihaanpundir/multitable/issues
Platform: UNKNOWN
Classifier: Programming Language :: Python :: 3
Classifier: License :: OSI Approved :: MIT License
Classifier: Operating System :: OS Independent
Requires-Python: >=3.8
License-File: LICENSE.txt
